{
  "size": 18919,
  "gzipSize": 1884,
  "rules": {
    "total": 279,
    "size": {
      "average": 2.057347670250896,
      "max": 8
    }
  },
  "selectors": {
    "total": 373,
    "type": 0,
    "class": 373,
    "id": 0,
    "pseudoClass": 1,
    "pseudoElement": 0,
    "values": [
      ".bx--grid",
      ".bx--grid",
      ".bx--grid--full-width",
      ".bx--row",
      ".bx--grid--condensed .bx--row:not(:last-of-type)",
      ".bx--row--condensed+.bx--row--condensed",
      ".bx--col",
      ".bx--grid--condensed .bx--col",
      ".bx--row--condensed .bx--col",
      ".bx--col-sm-1",
      ".bx--grid--condensed .bx--col-sm-1",
      ".bx--row--condensed .bx--col-sm-1",
      ".bx--col-sm-2",
      ".bx--grid--condensed .bx--col-sm-2",
      ".bx--row--condensed .bx--col-sm-2",
      ".bx--col-sm-3",
      ".bx--grid--condensed .bx--col-sm-3",
      ".bx--row--condensed .bx--col-sm-3",
      ".bx--col-sm-4",
      ".bx--grid--condensed .bx--col-sm-4",
      ".bx--row--condensed .bx--col-sm-4",
      ".bx--col-sm",
      ".bx--col-sm--auto",
      ".bx--grid--condensed .bx--col-sm",
      ".bx--grid--condensed .bx--col-sm--auto",
      ".bx--row--condensed .bx--col-sm",
      ".bx--row--condensed .bx--col-sm--auto",
      ".bx--col",
      ".bx--col-sm",
      ".bx--col--auto",
      ".bx--col-sm--auto",
      ".bx--col-sm-1",
      ".bx--col-sm-2",
      ".bx--col-sm-3",
      ".bx--col-sm-4",
      ".bx--offset-sm-0",
      ".bx--offset-sm-1",
      ".bx--offset-sm-2",
      ".bx--offset-sm-3",
      ".bx--col-md-1",
      ".bx--grid--condensed .bx--col-md-1",
      ".bx--row--condensed .bx--col-md-1",
      ".bx--col-md-2",
      ".bx--grid--condensed .bx--col-md-2",
      ".bx--row--condensed .bx--col-md-2",
      ".bx--col-md-3",
      ".bx--grid--condensed .bx--col-md-3",
      ".bx--row--condensed .bx--col-md-3",
      ".bx--col-md-4",
      ".bx--grid--condensed .bx--col-md-4",
      ".bx--row--condensed .bx--col-md-4",
      ".bx--col-md-5",
      ".bx--grid--condensed .bx--col-md-5",
      ".bx--row--condensed .bx--col-md-5",
      ".bx--col-md-6",
      ".bx--grid--condensed .bx--col-md-6",
      ".bx--row--condensed .bx--col-md-6",
      ".bx--col-md-7",
      ".bx--grid--condensed .bx--col-md-7",
      ".bx--row--condensed .bx--col-md-7",
      ".bx--col-md-8",
      ".bx--grid--condensed .bx--col-md-8",
      ".bx--row--condensed .bx--col-md-8",
      ".bx--col-md",
      ".bx--col-md--auto",
      ".bx--grid--condensed .bx--col-md",
      ".bx--grid--condensed .bx--col-md--auto",
      ".bx--row--condensed .bx--col-md",
      ".bx--row--condensed .bx--col-md--auto",
      ".bx--col",
      ".bx--col-md",
      ".bx--col--auto",
      ".bx--col-md--auto",
      ".bx--col-md-1",
      ".bx--col-md-2",
      ".bx--col-md-3",
      ".bx--col-md-4",
      ".bx--col-md-5",
      ".bx--col-md-6",
      ".bx--col-md-7",
      ".bx--col-md-8",
      ".bx--offset-md-0",
      ".bx--offset-md-1",
      ".bx--offset-md-2",
      ".bx--offset-md-3",
      ".bx--offset-md-4",
      ".bx--offset-md-5",
      ".bx--offset-md-6",
      ".bx--offset-md-7",
      ".bx--col-lg-1",
      ".bx--grid--condensed .bx--col-lg-1",
      ".bx--row--condensed .bx--col-lg-1",
      ".bx--col-lg-2",
      ".bx--grid--condensed .bx--col-lg-2",
      ".bx--row--condensed .bx--col-lg-2",
      ".bx--col-lg-3",
      ".bx--grid--condensed .bx--col-lg-3",
      ".bx--row--condensed .bx--col-lg-3",
      ".bx--col-lg-4",
      ".bx--grid--condensed .bx--col-lg-4",
      ".bx--row--condensed .bx--col-lg-4",
      ".bx--col-lg-5",
      ".bx--grid--condensed .bx--col-lg-5",
      ".bx--row--condensed .bx--col-lg-5",
      ".bx--col-lg-6",
      ".bx--grid--condensed .bx--col-lg-6",
      ".bx--row--condensed .bx--col-lg-6",
      ".bx--col-lg-7",
      ".bx--grid--condensed .bx--col-lg-7",
      ".bx--row--condensed .bx--col-lg-7",
      ".bx--col-lg-8",
      ".bx--grid--condensed .bx--col-lg-8",
      ".bx--row--condensed .bx--col-lg-8",
      ".bx--col-lg-9",
      ".bx--grid--condensed .bx--col-lg-9",
      ".bx--row--condensed .bx--col-lg-9",
      ".bx--col-lg-10",
      ".bx--grid--condensed .bx--col-lg-10",
      ".bx--row--condensed .bx--col-lg-10",
      ".bx--col-lg-11",
      ".bx--grid--condensed .bx--col-lg-11",
      ".bx--row--condensed .bx--col-lg-11",
      ".bx--col-lg-12",
      ".bx--grid--condensed .bx--col-lg-12",
      ".bx--row--condensed .bx--col-lg-12",
      ".bx--col-lg-13",
      ".bx--grid--condensed .bx--col-lg-13",
      ".bx--row--condensed .bx--col-lg-13",
      ".bx--col-lg-14",
      ".bx--grid--condensed .bx--col-lg-14",
      ".bx--row--condensed .bx--col-lg-14",
      ".bx--col-lg-15",
      ".bx--grid--condensed .bx--col-lg-15",
      ".bx--row--condensed .bx--col-lg-15",
      ".bx--col-lg-16",
      ".bx--grid--condensed .bx--col-lg-16",
      ".bx--row--condensed .bx--col-lg-16",
      ".bx--col-lg",
      ".bx--col-lg--auto",
      ".bx--grid--condensed .bx--col-lg",
      ".bx--grid--condensed .bx--col-lg--auto",
      ".bx--row--condensed .bx--col-lg",
      ".bx--row--condensed .bx--col-lg--auto",
      ".bx--col",
      ".bx--col-lg",
      ".bx--col--auto",
      ".bx--col-lg--auto",
      ".bx--col-lg-1",
      ".bx--col-lg-2",
      ".bx--col-lg-3",
      ".bx--col-lg-4",
      ".bx--col-lg-5",
      ".bx--col-lg-6",
      ".bx--col-lg-7",
      ".bx--col-lg-8",
      ".bx--col-lg-9",
      ".bx--col-lg-10",
      ".bx--col-lg-11",
      ".bx--col-lg-12",
      ".bx--col-lg-13",
      ".bx--col-lg-14",
      ".bx--col-lg-15",
      ".bx--col-lg-16",
      ".bx--offset-lg-0",
      ".bx--offset-lg-1",
      ".bx--offset-lg-2",
      ".bx--offset-lg-3",
      ".bx--offset-lg-4",
      ".bx--offset-lg-5",
      ".bx--offset-lg-6",
      ".bx--offset-lg-7",
      ".bx--offset-lg-8",
      ".bx--offset-lg-9",
      ".bx--offset-lg-10",
      ".bx--offset-lg-11",
      ".bx--offset-lg-12",
      ".bx--offset-lg-13",
      ".bx--offset-lg-14",
      ".bx--offset-lg-15",
      ".bx--col-xlg-1",
      ".bx--grid--condensed .bx--col-xlg-1",
      ".bx--row--condensed .bx--col-xlg-1",
      ".bx--col-xlg-2",
      ".bx--grid--condensed .bx--col-xlg-2",
      ".bx--row--condensed .bx--col-xlg-2",
      ".bx--col-xlg-3",
      ".bx--grid--condensed .bx--col-xlg-3",
      ".bx--row--condensed .bx--col-xlg-3",
      ".bx--col-xlg-4",
      ".bx--grid--condensed .bx--col-xlg-4",
      ".bx--row--condensed .bx--col-xlg-4",
      ".bx--col-xlg-5",
      ".bx--grid--condensed .bx--col-xlg-5",
      ".bx--row--condensed .bx--col-xlg-5",
      ".bx--col-xlg-6",
      ".bx--grid--condensed .bx--col-xlg-6",
      ".bx--row--condensed .bx--col-xlg-6",
      ".bx--col-xlg-7",
      ".bx--grid--condensed .bx--col-xlg-7",
      ".bx--row--condensed .bx--col-xlg-7",
      ".bx--col-xlg-8",
      ".bx--grid--condensed .bx--col-xlg-8",
      ".bx--row--condensed .bx--col-xlg-8",
      ".bx--col-xlg-9",
      ".bx--grid--condensed .bx--col-xlg-9",
      ".bx--row--condensed .bx--col-xlg-9",
      ".bx--col-xlg-10",
      ".bx--grid--condensed .bx--col-xlg-10",
      ".bx--row--condensed .bx--col-xlg-10",
      ".bx--col-xlg-11",
      ".bx--grid--condensed .bx--col-xlg-11",
      ".bx--row--condensed .bx--col-xlg-11",
      ".bx--col-xlg-12",
      ".bx--grid--condensed .bx--col-xlg-12",
      ".bx--row--condensed .bx--col-xlg-12",
      ".bx--col-xlg-13",
      ".bx--grid--condensed .bx--col-xlg-13",
      ".bx--row--condensed .bx--col-xlg-13",
      ".bx--col-xlg-14",
      ".bx--grid--condensed .bx--col-xlg-14",
      ".bx--row--condensed .bx--col-xlg-14",
      ".bx--col-xlg-15",
      ".bx--grid--condensed .bx--col-xlg-15",
      ".bx--row--condensed .bx--col-xlg-15",
      ".bx--col-xlg-16",
      ".bx--grid--condensed .bx--col-xlg-16",
      ".bx--row--condensed .bx--col-xlg-16",
      ".bx--col-xlg",
      ".bx--col-xlg--auto",
      ".bx--grid--condensed .bx--col-xlg",
      ".bx--grid--condensed .bx--col-xlg--auto",
      ".bx--row--condensed .bx--col-xlg",
      ".bx--row--condensed .bx--col-xlg--auto",
      ".bx--col",
      ".bx--col-xlg",
      ".bx--col--auto",
      ".bx--col-xlg--auto",
      ".bx--col-xlg-1",
      ".bx--col-xlg-2",
      ".bx--col-xlg-3",
      ".bx--col-xlg-4",
      ".bx--col-xlg-5",
      ".bx--col-xlg-6",
      ".bx--col-xlg-7",
      ".bx--col-xlg-8",
      ".bx--col-xlg-9",
      ".bx--col-xlg-10",
      ".bx--col-xlg-11",
      ".bx--col-xlg-12",
      ".bx--col-xlg-13",
      ".bx--col-xlg-14",
      ".bx--col-xlg-15",
      ".bx--col-xlg-16",
      ".bx--offset-xlg-0",
      ".bx--offset-xlg-1",
      ".bx--offset-xlg-2",
      ".bx--offset-xlg-3",
      ".bx--offset-xlg-4",
      ".bx--offset-xlg-5",
      ".bx--offset-xlg-6",
      ".bx--offset-xlg-7",
      ".bx--offset-xlg-8",
      ".bx--offset-xlg-9",
      ".bx--offset-xlg-10",
      ".bx--offset-xlg-11",
      ".bx--offset-xlg-12",
      ".bx--offset-xlg-13",
      ".bx--offset-xlg-14",
      ".bx--offset-xlg-15",
      ".bx--col-max-1",
      ".bx--grid--condensed .bx--col-max-1",
      ".bx--row--condensed .bx--col-max-1",
      ".bx--col-max-2",
      ".bx--grid--condensed .bx--col-max-2",
      ".bx--row--condensed .bx--col-max-2",
      ".bx--col-max-3",
      ".bx--grid--condensed .bx--col-max-3",
      ".bx--row--condensed .bx--col-max-3",
      ".bx--col-max-4",
      ".bx--grid--condensed .bx--col-max-4",
      ".bx--row--condensed .bx--col-max-4",
      ".bx--col-max-5",
      ".bx--grid--condensed .bx--col-max-5",
      ".bx--row--condensed .bx--col-max-5",
      ".bx--col-max-6",
      ".bx--grid--condensed .bx--col-max-6",
      ".bx--row--condensed .bx--col-max-6",
      ".bx--col-max-7",
      ".bx--grid--condensed .bx--col-max-7",
      ".bx--row--condensed .bx--col-max-7",
      ".bx--col-max-8",
      ".bx--grid--condensed .bx--col-max-8",
      ".bx--row--condensed .bx--col-max-8",
      ".bx--col-max-9",
      ".bx--grid--condensed .bx--col-max-9",
      ".bx--row--condensed .bx--col-max-9",
      ".bx--col-max-10",
      ".bx--grid--condensed .bx--col-max-10",
      ".bx--row--condensed .bx--col-max-10",
      ".bx--col-max-11",
      ".bx--grid--condensed .bx--col-max-11",
      ".bx--row--condensed .bx--col-max-11",
      ".bx--col-max-12",
      ".bx--grid--condensed .bx--col-max-12",
      ".bx--row--condensed .bx--col-max-12",
      ".bx--col-max-13",
      ".bx--grid--condensed .bx--col-max-13",
      ".bx--row--condensed .bx--col-max-13",
      ".bx--col-max-14",
      ".bx--grid--condensed .bx--col-max-14",
      ".bx--row--condensed .bx--col-max-14",
      ".bx--col-max-15",
      ".bx--grid--condensed .bx--col-max-15",
      ".bx--row--condensed .bx--col-max-15",
      ".bx--col-max-16",
      ".bx--grid--condensed .bx--col-max-16",
      ".bx--row--condensed .bx--col-max-16",
      ".bx--col-max",
      ".bx--col-max--auto",
      ".bx--grid--condensed .bx--col-max",
      ".bx--grid--condensed .bx--col-max--auto",
      ".bx--row--condensed .bx--col-max",
      ".bx--row--condensed .bx--col-max--auto",
      ".bx--col",
      ".bx--col-max",
      ".bx--col--auto",
      ".bx--col-max--auto",
      ".bx--col-max-1",
      ".bx--col-max-2",
      ".bx--col-max-3",
      ".bx--col-max-4",
      ".bx--col-max-5",
      ".bx--col-max-6",
      ".bx--col-max-7",
      ".bx--col-max-8",
      ".bx--col-max-9",
      ".bx--col-max-10",
      ".bx--col-max-11",
      ".bx--col-max-12",
      ".bx--col-max-13",
      ".bx--col-max-14",
      ".bx--col-max-15",
      ".bx--col-max-16",
      ".bx--offset-max-0",
      ".bx--offset-max-1",
      ".bx--offset-max-2",
      ".bx--offset-max-3",
      ".bx--offset-max-4",
      ".bx--offset-max-5",
      ".bx--offset-max-6",
      ".bx--offset-max-7",
      ".bx--offset-max-8",
      ".bx--offset-max-9",
      ".bx--offset-max-10",
      ".bx--offset-max-11",
      ".bx--offset-max-12",
      ".bx--offset-max-13",
      ".bx--offset-max-14",
      ".bx--offset-max-15",
      ".bx--no-gutter",
      ".bx--row.bx--no-gutter [class*=bx--col]",
      ".bx--no-gutter--left",
      ".bx--row.bx--no-gutter--left [class*=bx--col]",
      ".bx--no-gutter--right",
      ".bx--row.bx--no-gutter--right [class*=bx--col]",
      ".bx--hang--left",
      ".bx--hang--right",
      ".bx--aspect-ratio",
      ".bx--aspect-ratio--object",
      ".bx--aspect-ratio--16x9",
      ".bx--aspect-ratio--2x1",
      ".bx--aspect-ratio--4x3",
      ".bx--aspect-ratio--1x1"
    ],
    "specificity": {
      "max": 30,
      "average": 14.048257372654156
    }
  },
  "declarations": {
    "total": 574,
    "unique": 83,
    "properties": [
      "margin-right",
      "margin-left",
      "max-width",
      "padding-left",
      "padding-right",
      "display",
      "flex-wrap",
      "margin-bottom",
      "margin-top",
      "width",
      "flex-basis",
      "flex-grow",
      "flex",
      "height",
      "position",
      "top",
      "right",
      "bottom",
      "left",
      "z-index",
      "padding-bottom"
    ]
  },
  "mediaQueries": {
    "total": 6,
    "unique": 4,
    "values": [
      "(min-width:42rem)",
      "(min-width:99rem)",
      "(min-width:42rem)",
      "(min-width:66rem)",
      "(min-width:82rem)",
      "(min-width:99rem)"
    ]
  }
}
